{"name":"GET - Get Weather with valid endpoint and data","id":"explore\u0026monitoring-home;get---get-weather-with-valid-endpoint-and-data","testSteps":[{"number":1,"description":"Given I set GET api endpoints EmHome","duration":3384,"startTime":"2023-06-24T12:13:48.070+07:00[Asia/Bangkok]","result":"SUCCESS","precondition":false,"level":0,"children":[{"number":2,"description":"I set GET api endpoints EmHome","duration":15,"startTime":"2023-06-24T12:13:51.423+07:00[Asia/Bangkok]","result":"SUCCESS","precondition":false,"level":1}]},{"number":3,"description":"When I send GET HTTP request EmHome","duration":10201,"startTime":"2023-06-24T12:13:51.475+07:00[Asia/Bangkok]","result":"SUCCESS","precondition":false,"level":0,"children":[{"number":4,"description":"When I send GET HTTP request EmHome","duration":10185,"startTime":"2023-06-24T12:13:51.475+07:00[Asia/Bangkok]","result":"SUCCESS","precondition":false,"level":1,"children":[{"number":5,"description":"I set GET api endpoints EmHome","duration":0,"startTime":"2023-06-24T12:13:57.300+07:00[Asia/Bangkok]","result":"SUCCESS","precondition":false,"level":2},{"number":6,"description":"GET https://34.128.85.215:8080/auth/users/weather/-3.577847/102.346390\r","duration":0,"startTime":"2023-06-24T12:14:01.217+07:00[Asia/Bangkok]","result":"SUCCESS","restQuery":{"method":"GET","path":"https://34.128.85.215:8080/auth/users/weather/-3.577847/102.346390\r","content":"\r","contentType":"null","requestHeaders":"Authorization\u003dBearer eyJhbGciOiJIUzI1NiIsInR5cCI6IkpXVCJ9.eyJuYW1lIjoiYW5ha3FlIiwicm9sZSI6InVzZXIiLCJ1c2VyX2lkIjozfQ.d_DwYth9wp72Dax1p3XBVTxtOWldjOMnn-6cqYfiQjA\r\n\t\t\t\tAccept\u003d*/*\r","requestCookies":"\r","responseHeaders":"Content-Type: application/json; charset\u003dUTF-8\r\nVary: Origin\r\nDate: Sat, 24 Jun 2023 05:14:00 GMT\r\nContent-Length: 168\r","responseCookies":"\r","responseBody":"{\n    \"data\": {\n        \"city\": \"Curup\",\n        \"country\": \"Indonesia\",\n        \"label\": \"Berawan\",\n        \"label_id\": 4,\n        \"temperature\": \"29.83\"\n    },\n    \"message\": \"successfully obtained weather information\",\n    \"status\": 200\n}","statusCode":200},"precondition":false,"level":2}]}]},{"number":7,"description":"Then I receive valid HTTP response code 200","duration":94,"startTime":"2023-06-24T12:14:01.676+07:00[Asia/Bangkok]","result":"SUCCESS","precondition":false,"level":0,"children":[{"number":8,"description":"I receive valid HTTP response code 200","duration":2,"startTime":"2023-06-24T12:14:01.766+07:00[Asia/Bangkok]","result":"SUCCESS","precondition":false,"level":1}]}],"userStory":{"id":"explore\u0026monitoring-home","storyName":"Explore\u0026Monitoring Home","path":"EmHome.feature","narrative":"  As a user\n  I want to grow plants\n  So that I should access Explore\u0026Monitoring","type":"feature"},"featureTag":{"name":"Explore\u0026Monitoring Home","type":"feature","displayName":"Explore\u0026Monitoring Home"},"title":"GET - Get Weather with valid endpoint and data","description":"","tags":[{"name":"EmHome","type":"tag","displayName":"EmHome"},{"name":"Explore\u0026Monitoring Home","type":"feature","displayName":"Explore\u0026Monitoring Home"}],"startTime":"2023-06-24T12:13:47.070+07:00[Asia/Bangkok]","duration":14706,"projectKey":"","isManualTestingUpToDate":false,"manual":false,"testSource":"Cucumber","result":"SUCCESS"}